habitat_baselines/__init__.py
habitat_baselines/py.typed
habitat_baselines/run.py
habitat_baselines/version.py
habitat_baselines/agents/__init__.py
habitat_baselines/agents/ppo_agents.py
habitat_baselines/agents/simple_agents.py
habitat_baselines/articulated_agent_controllers/__init__.py
habitat_baselines/articulated_agent_controllers/humanoid_rearrange_controller.py
habitat_baselines/common/__init__.py
habitat_baselines/common/base_il_trainer.py
habitat_baselines/common/base_trainer.py
habitat_baselines/common/baseline_registry.py
habitat_baselines/common/construct_vector_env.py
habitat_baselines/common/env_spec.py
habitat_baselines/common/logging.py
habitat_baselines/common/obs_transformers.py
habitat_baselines/common/rollout_storage.py
habitat_baselines/common/storage.py
habitat_baselines/common/tensor_dict.py
habitat_baselines/common/tensorboard_utils.py
habitat_baselines/common/windowed_running_mean.py
habitat_baselines/config/__init__.py
habitat_baselines/config/default.py
habitat_baselines/config/default_structured_configs.py
habitat_baselines/il/__init__.py
habitat_baselines/il/metrics.py
habitat_baselines/il/requirements.txt
habitat_baselines/il/data/__init__.py
habitat_baselines/il/data/data.py
habitat_baselines/il/data/eqa_cnn_pretrain_data.py
habitat_baselines/il/data/nav_data.py
habitat_baselines/il/models/__init__.py
habitat_baselines/il/models/models.py
habitat_baselines/il/trainers/__init__.py
habitat_baselines/il/trainers/eqa_cnn_pretrain_trainer.py
habitat_baselines/il/trainers/pacman_trainer.py
habitat_baselines/il/trainers/vqa_trainer.py
habitat_baselines/rl/__init__.py
habitat_baselines/rl/requirements.txt
habitat_baselines/rl/ddppo/__init__.py
habitat_baselines/rl/ddppo/ddp_utils.py
habitat_baselines/rl/ddppo/requirements.txt
habitat_baselines/rl/ddppo/algo/__init__.py
habitat_baselines/rl/ddppo/algo/ddppo.py
habitat_baselines/rl/ddppo/policy/__init__.py
habitat_baselines/rl/ddppo/policy/resnet.py
aihabitat_baselines-0.2.4.dev20230331.dist-info/METADATA
aihabitat_baselines-0.2.4.dev20230331.dist-info/WHEEL
aihabitat_baselines-0.2.4.dev20230331.dist-info/entry_points.txt
aihabitat_baselines-0.2.4.dev20230331.dist-info/top_level.txt
aihabitat_baselines-0.2.4.dev20230331.dist-info/RECORD
