Metadata-Version: 2.1
Name: aihabitat-baselines
Version: 0.2.4.dev20230331
Summary: Habitat-Baselines: Embodied AI baselines.
Home-page: https://aihabitat.org
Author: Meta AI Research
License: MIT License
Project-URL: GitHub repo, https://github.com/facebookresearch/habitat-lab/
Project-URL: Bug Tracker, https://github.com/facebookresearch/habitat-lab/issues
Classifier: Intended Audience :: Science/Research
Classifier: Development Status :: 5 - Production/Stable
Classifier: License :: OSI Approved :: MIT License
Classifier: Topic :: Scientific/Engineering :: Artificial Intelligence
Classifier: Programming Language :: Python
Classifier: Programming Language :: Python :: 3
Classifier: Programming Language :: Python :: 3.9
Classifier: Programming Language :: Python :: 3.10
Classifier: Programming Language :: Python :: 3.11
Classifier: Intended Audience :: Developers
Classifier: Intended Audience :: Education
Classifier: Intended Audience :: Science/Research
Classifier: Operating System :: MacOS
Classifier: Operating System :: Unix
Requires-Dist: faster-fifo (>=1.4.2)
Requires-Dist: moviepy (>=1.0.1)
Requires-Dist: ifcfg
Requires-Dist: torch (>=1.3.1)
Requires-Dist: tensorboard (==2.8.0)
Requires-Dist: threadpoolctl (>=3.1.0)
Requires-Dist: protobuf (==3.20.1)
Requires-Dist: lmdb (>=0.98)
Requires-Dist: webdataset (==0.1.40)
